{
	"type": "FeatureCollection",
	"features": [
		{"geometry":{"coordinates":[-3.54307,54.64285],"type":"Point"},"properties":{"_source":"warm_welcome","address":"St. Johns Church, Cumbria CA14 3AW","description":"The space is open to all","hours":{"_text":"Wednesday: 10:30 - 12:45","opening":"We 10:30-12:45"},"title":"St John's Church Community Hall"},"type":"Feature"},
		{"geometry":{"coordinates":[-3.56430,54.61845],"type":"Point"},"properties":{"_source":"warm_welcome","address":"The Riverside Group Ltd, Workington, Cumbria CA14 5HA","description":"Cafe at the Oval Centre","hours":{"_text":"Monday: 11:00 - 14:00, Tuesday: 11:00 - 14:00, Wednesday: 11:00 - 14:00, Thursday: 11:00 - 14:00, Friday: 11:00 - 14:00","opening":"Mo 11:00-14:00; Tu 11:00-14:00; We 11:00-14:00; Th 11:00-14:00; Fr 11:00-14:00"},"title":"The Oval Centre"},"type":"Feature"},
		{"geometry":{"coordinates":[-3.56430,54.61845],"type":"Point"},"properties":{"_source":"warm_welcome","address":"The Riverside Group Ltd, Workington, Cumbria CA14 5HA","description":"SPACE OPENING ON 19th November 2025** The Oval Centre is a community hub designed to bring people together for social, educational, and creative activities. It typically serves as a welcoming space for local residents to access resources, attend events, and participate in programs that promote wellbeing, learning and community engagement.","hours":{"_text":"Wednesday: 10:00 - 12:00, Thursday: 10:00 - 13:00, Friday: 10:00 - 13:00","opening":"We 10:00-12:00; Th 10:00-13:00; Fr 10:00-13:00"},"title":"The Oval Centre"},"type":"Feature"}
	]
}
