{
	"type": "FeatureCollection",
	"features": [
		{"geometry":{"coordinates":[-3.54307,54.64285],"type":"Point"},"properties":{"_source":"warm_welcome","address":"St. Johns Church, Cumbria CA14 3AW","description":"The space is open to all","hours":{"_text":"Wednesday: 10:30 - 12:45","opening":"We 10:30-12:45"},"title":"St John's Church Community Hall"},"type":"Feature"}
	]
}
