{
	"type": "FeatureCollection",
	"features": [
		{"geometry":{"coordinates":[-3.54307,54.64285],"type":"Point"},"properties":{"_source":"warm_welcome","address":"St. Johns Church, Cumbria CA14 3AW","description":"The space is open to all","hours":{"_text":"Wednesday: 10:30 - 12:45","opening":"We 10:30-12:45"},"title":"St John's Church Community Hall"},"type":"Feature"},
		{"geometry":{"coordinates":[-3.55958,54.63089],"type":"Point"},"properties":{"_source":"warm_welcome","address":"St.Mary's Church, Salisbury Street Workington, Cumbria CA14 3TR","description":"Warm and welcoming space in the parish centre. Offering hot drinks and toast. Newspapers. Access to the internet. Board games. Good company.","hours":{"_text":"Wednesday: 09:00 - 11:30","opening":"We 09:00-11:30"},"title":"Warm Welcome St. Mary's Westfield"},"type":"Feature"},
		{"geometry":{"coordinates":[-3.54548,54.64586],"type":"Point"},"properties":{"_source":"warm_welcome","address":"Workington Leisure Centre, Cumbria CA14 2DX","description":"We would like to be able to provide a warm space for people to come and sit, enjoy company, play games and take part in some activities in the centre.","hours":{"_text":"Tuesday: 10:00 - 14:00, Thursday: 10:00 - 14:00","opening":"Tu 10:00-14:00; Th 10:00-14:00"},"title":"Workington Leisure Centre"},"type":"Feature"}
	]
}
