{
	"type": "FeatureCollection",
	"features": [
		{"geometry":{"coordinates":[-3.59693,52.91310],"type":"Point"},"properties":{"_source":"cyngor_gwynedd","address":"Campws Ysgol Y Berwyn Campus, Heol Ffrydan, Y Bala, Gwynedd, LL23 7RU","contact":"Tel: 01678 520014; Email: LlBala@gwynedd.llyw.cymru","description":"Defnydd o stafell gynnes / The use of a warm room, WIFI, Gweithgareddau / Activities","hours":{"_text":"Llun/Monday - 2.00-6.00\nMawrth/Iau - Tuesday/Thursday - 10.30-1.00 2.00-5.00\nGwener/Friday - 2.00-5.00\nSadwrn/Saturday - 10.00-12.00","opening":"Tu 10:30-01:00; Th 10:30-01:00; Mo 02:00-06:00; Fr 02:00-05:00; Sa 10:00-12:00"},"name":"Llyfrgell Y Bala Library"},"type":"Feature"},
		{"geometry":{"coordinates":[-3.59840,52.91527],"type":"Point"},"properties":{"_source":"cyngor_gwynedd","address":"Cysgod y Coleg, Y Bala, LL23 7BD","contact":"Tel: 0300 123 8084; Email: ymholiadau@adra.co.uk","description":"Defnydd o stafell gynnes / The use of a warm room","hours":{"_text":"Dydd Mercher 12pm-3:30pm\nWednesdays 12pm-3:30pm","opening":"We 12:00-15:30"},"name":"Cysgod y Coleg (Adra Tai)"},"type":"Feature"},
		{"geometry":{"coordinates":[-3.60392,52.91432],"type":"Point"},"properties":{"_source":"cyngor_gwynedd","address":"Castle Park, Castle Street, Y Bala,, LL23 7UW","contact":"Tel: 07794589824; Email: office.balacommunityassociation@gmail.com","description":"Defnydd o stafell gynnes / The use of a warm room, Paned / Warm Beverage, Bwyd / Food, Arall / Other","hours":{"_text":"Bob dydd Iau 9:30 am - 11:30 am & 1:30 pm - 6:30 pm. // Every Thursday"},"name":"The Pavilion"},"type":"Feature"},
		{"geometry":{"coordinates":[-3.56105,53.02562],"type":"Point"},"properties":{"_source":"cyngor_gwynedd","address":"King Street Cerrigydrudion Corwen LL21 9TF, LL21 9TF","contact":"Tel: 01492 577547; Email: cerrig.library@conwy.gov.uk","description":"Paned / Warm Beverage, Bwyd / Food, WIFI","hours":{"_text":"Dydd Mawrth // Tuesdays - 10:30pm - 12:30pm","opening":"Tu 22:30-12:30"},"name":"Cerrigydrudion Library"},"type":"Feature"}
	]
}
