{
	"type": "FeatureCollection",
	"features": [
		{"geometry":{"coordinates":[-3.59693,52.91309],"type":"Point"},"properties":{"_source":"cyngor_gwynedd","address":"Campws Ysgol Y Berwyn Campus, Heol Ffrydan, Y Bala, Gwynedd, LL23 7RU","contact":"Tel: 01678 520014; Email: LlBala@gwynedd.llyw.cymru","description":"Cyfeiriad: Campws Ysgol Y Berwyn Campus, Heol Ffrydan, Y Bala, Gwynedd Côd Post: LL23 7RU Rhif Ffôn: 01678 520014 E-bost: LlBala@gwynedd.llyw.cymru Dyddiau ac Oriau agor: Llun/Monday - 2.00-6.00 Mawrth/Iau - Tuesday/Thursday - 10.30-1.00 2.00-5.00 Gwener/Friday - 2.00-5.00 Sadwrn/Saturday - 10.00-12.00 Beth fydd ar gael yn rhan o’ch “Croeso Cynnes”?: Defnydd o stafell gynnes / The use of a warm room, WIFI, Gweithgareddau / Activities Unrhyw fanylion pellach?:","hours":{"_text":"Llun/Monday - 2.00-6.00\nMawrth/Iau - Tuesday/Thursday - 10.30-1.00 2.00-5.00\nGwener/Friday - 2.00-5.00\nSadwrn/Saturday - 10.00-12.00","opening":"Tu 10:30-01:00; Th 10:30-01:00; Mo 02:00-06:00; Fr 02:00-05:00; Sa 10:00-12:00"},"loc_pcd":true,"title":"Llyfrgell Y Bala Library"},"type":"Feature"},
		{"geometry":{"coordinates":[-3.59839,52.91527],"type":"Point"},"properties":{"_source":"cyngor_gwynedd","address":"Cysgod y Coleg, Y Bala, LL23 7BD","contact":"Tel: 0300 123 8084; Email: ymholiadau@adra.co.uk","description":"Cyfeiriad: Cysgod y Coleg, Y Bala Côd Post: LL23 7BD Rhif Ffôn: 0300 123 8084 E-bost: ymholiadau@adra.co.uk Dyddiau ac Oriau agor: Dydd Mercher 12pm-3:30pm Wednesdays 12pm-3:30pm Beth fydd ar gael yn rhan o’ch “Croeso Cynnes”?: Defnydd o stafell gynnes / The use of a warm room Unrhyw fanylion pellach?:","hours":{"_text":"Dydd Mercher 12pm-3:30pm\nWednesdays 12pm-3:30pm","opening":"We 12:00-15:30"},"loc_pcd":true,"title":"Cysgod y Coleg (Adra Tai)"},"type":"Feature"}
	]
}
