{
	"type": "FeatureCollection",
	"features": [
		{"geometry":{"coordinates":[-1.63388,53.71419],"type":"Point"},"properties":{"_source":"warm_welcome","address":"14 Market Place, Batley, West Yorkshire WF17 5DA","description":" All our libraries are heated, comfortable to stay in for long periods of time - they have a range of both comfy seating, and more functional furniture for study or computer use. A place to keep warm, meet friends, sit and read and take part in activities.","hours":"Mo 10:00-19:00, Tu 10:00-17:00, Th 10:00-17:00, Fr 10:00-17:00, Sa 12:00-17:00","title":"Batley Library"},"type":"Feature"},
		{"geometry":{"coordinates":[-1.66102,53.73139],"type":"Point"},"properties":{"_source":"warm_welcome","address":"Market Street, Birstall, Batley, West Yorkshire WF17 9EN","description":" All our libraries are heated, comfortable to stay in for long periods of time - they have a range of both comfy seating, and more functional furniture for study or computer use. A place to keep warm, meet friends, sit and read and take part in activities.","hours":"Mo 10:00-13:00, Tu 10:00-17:00, We 10:00-19:00, Th 10:00-17:00, Fr 10:00-13:00, Sa 09:00-12:30","title":"Birstall Library"},"type":"Feature"}