{
	"type": "FeatureCollection",
	"features": [
		{"geometry":{"coordinates":[-1.58431,52.28191],"type":"Point"},"properties":{"_source":"warm_welcome","address":"Castle Hill, Castle Hill, Warwick CV34 4EX","description":"Open from 31-10-2022. A place to just 'be', with books, jigsaws, board games, craft materials - a Home From Home. Help yourself to free drinks and snacks. Visit our website for clubs on during the month.","hours":"Mo 12:30-15:30","title":"Castle Hill Baptist Church, Warwick"},"type":"Feature"}