{
	"type": "FeatureCollection",
	"features": [
		{"geometry":{"coordinates":[-2.02650,53.10660],"type":"Point"},"properties":{"_source":"warm_spaces","address":"Church Street, Leek, England, ST13 6AB, United Kingdom","description":"Free Food/Drink, Free Wi-Fi, Device Charging, People to chat to, Toilets, Wheelchair access between 9.00am and 2.00pm","hours":{"_text":"Wednesday 9am-5pm","opening":"We 09:00-17:00"},"title":"Saint Edward's Church, Leek","url":"https://leekparish.org.uk/churches/st-edwards-church/"},"type":"Feature"}
	]
}
