{
	"type": "FeatureCollection",
	"features": [
		{"geometry":{"coordinates":[-2.02511,53.10617],"type":"Point"},"properties":{"_source":"warm_welcome","address":"Market Hall, Leek, Staffordshire ST13 5HH","description":"OUTSIDE are a Creative People and Places project serving the communities of the Staffordshire Moorlands. Come along to our friendly and welcoming market stall for a chat and a brew. You can find out more about us, enjoy a jigsaw or craft or simply enjoy a hot drink while watching the shoppers pass by. Our stall, located in the newly refurbished Leek Butter Market, is open 8.30am-4pm on Wednesday, Friday and Saturday.","hours":{"_text":"Wednesday: 08:30 - 16:00, Friday: 08:30 - 16:00, Saturday: 08:30 - 16:00","opening":"We 08:30-16:00; Fr 08:30-16:00; Sa 08:30-16:00"},"title":"OUTSIDE - Leek Market Stall"},"type":"Feature"}
	]
}
