{
	"type": "FeatureCollection",
	"features": [
		{"geometry":{"coordinates":[-2.06044,52.96512],"type":"Point"},"properties":{"_source":"warm_welcome","address":"Methodist Church, Staffordshire ST11 9LZ","description":"We offer a warm welcome into our Church hall where we have refreshments, board games, craft activities, children’s toys/play area and space to sit and chat. All free of charge. Our team of volunteers love being there too and look forward to welcoming new guests.","hours":{"_text":"Tuesday: 15:00 - 17:00","opening":"Tu 15:00-17:00"},"title":"Warm Space at Blythe Bridge Methodist Church"},"type":"Feature"},
		{"geometry":{"coordinates":[-2.02650,53.10660],"type":"Point"},"properties":{"_source":"warm_spaces","address":"Church Street, Leek, England, ST13 6AB, United Kingdom","description":"Free Food/Drink, Free Wi-Fi, Device Charging, People to chat to, Toilets, Wheelchair access between 9.00am and 2.00pm","hours":{"_text":"Wednesday 9am-5pm","opening":"We 09:00-17:00"},"title":"Saint Edward's Church, Leek","url":"https://leekparish.org.uk/churches/st-edwards-church/"},"type":"Feature"}
	]
}
