{
	"type": "FeatureCollection",
	"features": [
		{"geometry":{"coordinates":[-2.02511,53.10617],"type":"Point"},"properties":{"_source":"warm_welcome","address":"Market Hall, Leek, Staffordshire ST13 5HH","description":"OUTSIDE are a Creative People and Places project serving the communities of the Staffordshire Moorlands. Come along to our friendly and welcoming market stall for a chat and a brew. You can find out more about us, enjoy a jigsaw or craft or simply enjoy a hot drink while watching the shoppers pass by. Our stall, located in the newly refurbished Leek Butter Market, is open 8.30am-4pm on Wednesday, Friday and Saturday.","hours":{"_text":"Wednesday: 08:30 - 16:00, Friday: 08:30 - 16:00, Saturday: 08:30 - 16:00","opening":"We 08:30-16:00; Fr 08:30-16:00; Sa 08:30-16:00"},"title":"OUTSIDE - Leek Market Stall"},"type":"Feature"},
		{"geometry":{"coordinates":[-2.06044,52.96512],"type":"Point"},"properties":{"_source":"warm_welcome","address":"Methodist Church, Staffordshire ST11 9LZ","description":"We offer a warm welcome into our Church hall where we have refreshments, board games, craft activities, children’s toys/play area and space to sit and chat. All free of charge. Our team of volunteers love being there too and look forward to welcoming new guests.","hours":{"_text":"Tuesday: 15:00 - 17:00","opening":"Tu 15:00-17:00"},"title":"Warm Space at Blythe Bridge Methodist Church"},"type":"Feature"},
		{"geometry":{"coordinates":[-1.83711,52.95204],"type":"Point"},"properties":{"_source":"east_staffordshire_council","address":"St Michaels Church, St Michael Church, Dove lane, Rocester, ST14 5JZ","hours":{"_text":"Monday from 10am to 4pm; Tuesday 1pm to 3.30pm; Thursday 10am to 3.30pm","opening":"Mo 10:00-16:00; Tu 13:00-15:30; Th 10:00-15:30"},"loc_pcd":true,"title":"St Michaels Church"},"type":"Feature"},
		{"geometry":{"coordinates":[-1.88432,52.91916],"type":"Point"},"properties":{"_source":"east_staffordshire_council","address":"Stramshall Village Hall, Vicarage Drive, Stramshall ST14 5DL","hours":{"_text":"Thursdays 10:45am to 12:45pm","opening":"Th 10:45-12:45"},"loc_pcd":true,"title":"Stramshall Village Hall"},"type":"Feature"}
	]
}
