{
	"type": "FeatureCollection",
	"features": [
		{"geometry":{"coordinates":[-2.06044,52.96512],"type":"Point"},"properties":{"_source":"warm_welcome","address":"Methodist Church, Staffordshire ST11 9LZ","description":"We offer a warm welcome into our Church hall where we have refreshments, board games, craft activities, children’s toys/play area and space to sit and chat. All free of charge. Our team of volunteers love being there too and look forward to welcoming new guests.","hours":{"_text":"Tuesday: 15:00 - 17:00","opening":"Tu 15:00-17:00"},"title":"Warm Space at Blythe Bridge Methodist Church"},"type":"Feature"}
	]
}
