{
	"type": "FeatureCollection",
	"features": [
		{"geometry":{"coordinates":[-1.99175,51.35114],"type":"Point"},"properties":{"_source":"warm_spaces","address":"Sheep Street, Devizes, England, SN10 1DL, United Kingdom","description":"Free Food/Drink, Free Wi-Fi, Device Charging, Advice, Space to work, Wheelchair Accessible, Toilets, Accessible Toilet, Child Friendly, Computer Access, Warm Pack - Blanket, thermal mug; hot water bottle and bag","hours":{"_text":"Mon 9.30-7pm; Tue 9.30-5pm; Wed 9.30-12.30pm; Thu 9.30-7pm; Fri 9.30-5pm; Sat 9.30-4pm","opening":"Mo 09:30-19:00; Tu 09:30-17:00; We 09:30-12:30; Th 09:30-19:00; Fr 09:30-17:00; Sa 09:30-16:00"},"title":"Devizes Library","url":"https://www.wiltshire.gov.uk"},"type":"Feature"},
		{"geometry":{"coordinates":[-2.10086,51.34862],"type":"Point"},"properties":{"_source":"warm_spaces","address":"The Brewery Inn, Seend Cleeve, Melksham, England, SN12 6PX, United Kingdom","description":"Free Wi-Fi, Space to work, Food/Drink for sale, Toilets, Free tea / coffee","hours":{"_text":"12noon-5pm"},"title":"Brewery Inn"},"type":"Feature"},
		{"geometry":{"coordinates":[-1.98064,51.28603],"type":"Point"},"properties":{"_source":"warm_spaces","address":"The Old School, Church Street, Devizes, England, SN10 4DT, United Kingdom","description":"Free Food/Drink, Free Wi-Fi, Device Charging, Advice, People to chat to, Space to work, Wheelchair Accessible, Toilets, Child Friendly","hours":{"_text":"Friday 10am-5pm","opening":"Fr 10:00-17:00"},"title":"The Old School Market Lavington"},"type":"Feature"}
	]
}
