{
	"type": "FeatureCollection",
	"features": [
		{"geometry":{"coordinates":[-1.97983,51.28629],"type":"Point"},"properties":{"_source":"warm_welcome","address":"The Old School Hall, Devizes, Wiltshire SN10 4DT","description":"The space is open to all","hours":{"_text":"Friday: 10:00 - 13:00","opening":"Fr 10:00-13:00"},"title":"Friendship Fridays"},"type":"Feature"},
		{"geometry":{"coordinates":[-1.99357,51.35046],"type":"Point"},"properties":{"_source":"warm_welcome","address":"St Andrews Church , Devizes, Wiltshire SN10 1NJ","description":"A warm and accessible space with facilities for wheelchair users and carers of young children. Hot drinks, snacks and easy going conversation available in a place that is open to all.","hours":{"_text":"Thursday: 09:30 - 11:30","opening":"Th 09:30-11:30"},"title":"St Andrews Church"},"type":"Feature"},
		{"geometry":{"coordinates":[-1.76685,51.34021],"type":"Point"},"properties":{"_source":"wiltshire_council","description":"A place to meet for tea and cake","title":"Renew Wellbeing Cafe - Pewsey Methodist Church","url":"https://directory.hertfordshire.gov.uk/Services/2114"},"type":"Feature"},
		{"geometry":{"coordinates":[-1.99483,51.34891],"type":"Point"},"properties":{"_source":"wiltshire_council","description":"Nature-based activities for people struggling with mental health issues","title":"Wiltshire Wildlife Trust - Wellbeing Programme","url":"https://directory.hertfordshire.gov.uk/Services/66"},"type":"Feature"}
	]
}
