{
	"type": "FeatureCollection",
	"features": [
		{"geometry":{"coordinates":[-1.99382,51.35042],"type":"Point"},"properties":{"_source":"warm_welcome","address":"St Andrews Church, Long Street , Devizes, Wiltshire SN10 1NJ","description":"A Climate Cafe meeting in an adjacent space that is open to all.","hours":{"_text":"Thursday: 09:30 - 14:00","opening":"Th 09:30-14:00"},"title":"St Andrews Church"},"type":"Feature"},
		{"geometry":{"coordinates":[-1.97920,51.28633],"type":"Point"},"properties":{"_source":"warm_welcome","address":"1 Church Street, Market Lavington, Wilts SN10 4DT","description":"It's small but beautifully formed & friendly.","hours":{"_text":"Monday: 10:00 - 16:30, Tuesday: 10:00 - 16:30, Wednesday: 10:00 - 16:30, Friday: 10:00 - 16:30, Saturday: 10:00 - 13:00","opening":"Mo 10:00-16:30; Tu 10:00-16:30; We 10:00-16:30; Fr 10:00-16:30; Sa 10:00-13:00"},"title":"St. Arbucks Community Cafe"},"type":"Feature"},
		{"geometry":{"coordinates":[-1.99483,51.34891],"type":"Point"},"properties":{"_source":"wiltshire_council","description":"Nature-based activities for people struggling with mental health issues","title":"Wiltshire Wildlife Trust - Wellbeing Programme","url":"https://directory.hertfordshire.gov.uk/Services/66"},"type":"Feature"},
		{"geometry":{"coordinates":[-1.76685,51.34021],"type":"Point"},"properties":{"_source":"wiltshire_council","description":"A place to meet over a cuppa cake and free games and activities - all welcome","title":"Renew Wellbeing Caf&#233; - Pewsey Methodist Church","url":"https://directory.hertfordshire.gov.uk/Services/2114"},"type":"Feature"}
	]
}
