{
	"type": "FeatureCollection",
	"features": [
		{"geometry":{"coordinates":[-1.99300,51.34940],"type":"Point"},"properties":{"_source":"warm_welcome","address":"Long Street , Devizes, Wiltshire SN10 1NJ","description":"A Climate Cafe meeting in an adjacent space that is open to all.","hours":{"_text":"Thursday: 09:30 - 14:00","opening":"Th 09:30-14:00"},"title":"St Andrews Church"},"type":"Feature"},
		{"geometry":{"coordinates":[-2.10086,51.34862],"type":"Point"},"properties":{"_source":"warm_spaces","address":"The Brewery Inn, Seend Cleeve, Melksham, England, SN12 6PX","hours":{"_text":"12noon-5pm "},"title":"Brewery Inn"},"type":"Feature"},
		{"geometry":{"coordinates":[-1.98064,51.28603],"type":"Point"},"properties":{"_source":"warm_spaces","address":"The Old School, Church Street, Devizes, England, SN10 4DT","hours":{"_text":"Friday 10am-5pm ","opening":"Fr 10:00-17:00"},"title":"The Old School Market Lavington"},"type":"Feature"}
	]
}
