{
	"type": "FeatureCollection",
	"features": [
		{"geometry":{"coordinates":[-5.09151,50.05114],"type":"Point"},"properties":{"_source":"warm_welcome","address":"United Methodist Church St Keverne, St Keverne, Cornwall TR 12 6QD","description":"Open coffee mornings once a month open to all. A warm welcome is for all and coffee, tea and biscuits on offer. Donations accepted. A warm hub luncheon club with a two course meal is freely available with activities 3 times a month.","hours":{"_text":"Monday: 10:30 - 02:00, Saturday: 10:00 - 12:00 Monthly","opening":"Mo 10:30-02:00; Sa 10:00-12:00"},"title":"United Methodist Church St Keverne"},"type":"Feature"},
		{"geometry":{"coordinates":[-5.24084,50.02780],"type":"Point"},"properties":{"_source":"carefree_cornwall","address":"Mullion Methodist Church, Churchtown, Mullion, Helston, TR12 7BT","description":"ICA Area: West Cornwall Area: Kerrier Hub Area: Helston & The Lizard Address: Mullion Methodist Church, Churchtown, Mullion, Helston, TR12 7BT Opening Times: Fri 10:00 - 12:00 Activities Offered: Public Contact Name: David Williams Public Phone: 01326 564194 Public Email: mustardseed@post.com Notes: Health Checks: Pain or Cancer Café: Diabetes Support: Falls or Balance: Cardio or Respiratory Groups: Dementia Support: Physical Activity: Hospital Discharge: Growing and Cooking: Transport Provision: Hub Partnership: Carer Support: Outreach with Neighbourhoods: Enhanced PCN Relationship: Meals on Wheels: Debt or Legal Advice: Talking Therapies: Vaccination Clinics: Digital Offer: Children, Young People and Family Hubs: Other Additional Service (Specify):","loc_pcd":true,"title":"Mustard Seed"},"type":"Feature"}
	]
}
