{
	"type": "FeatureCollection",
	"features": [
		{"geometry":{"coordinates":[-5.24084,50.02780],"type":"Point"},"properties":{"_source":"carefree_cornwall","address":"Mullion Methodist Church, Churchtown, Mullion, Helston, TR12 7BT","description":"ICA Area: West Cornwall Area: Kerrier Hub Area: Helston & The Lizard Address: Mullion Methodist Church, Churchtown, Mullion, Helston, TR12 7BT Opening Times: Fri 10:00 - 12:00 Activities Offered: Public Contact Name: David Williams Public Phone: 01326 564194 Public Email: mustardseed@post.com Notes: Health Checks: Pain or Cancer Café: Diabetes Support: Falls or Balance: Cardio or Respiratory Groups: Dementia Support: Physical Activity: Hospital Discharge: Growing and Cooking: Transport Provision: Hub Partnership: Carer Support: Outreach with Neighbourhoods: Enhanced PCN Relationship: Meals on Wheels: Debt or Legal Advice: Talking Therapies: Vaccination Clinics: Digital Offer: Children, Young People and Family Hubs: Other Additional Service (Specify):","loc_pcd":true,"title":"Mustard Seed"},"type":"Feature"}
	]
}
