{
	"type": "FeatureCollection",
	"features": [
		{"geometry":{"coordinates":[-1.05215,54.53578],"type":"Point"},"properties":{"_source":"warm_welcome","address":"4 - 6 Westgate , Guisbrough , Cleveland TS14 6BA","hours":{"_text":"Monday: 09:00 - 6:00, Tuesday: 09:00 - 16:00, Wednesday: 09:00 - 16:00, Thursday: 09:00 - 16:00, Friday: 09:00 - 16:00","opening":"Mo 09:00-06:00; Tu 09:00-16:00; We 09:00-16:00; Th 09:00-16:00; Fr 09:00-16:00"},"title":"Brickyard Bakery cic"},"type":"Feature"},
		{"geometry":{"coordinates":[-0.90711,54.46871],"type":"Point"},"properties":{"_source":"warm_welcome","address":"Danby Village Hall, Dale End, Danby, Whitby YO21 2LZ","title":"Revival North Yorkshire"},"type":"Feature"},
		{"geometry":{"coordinates":[-0.98398,54.56204],"type":"Point"},"properties":{"_source":"warm_spaces","address":"Skelton Civic Hall, 20 Coniston Road, Saltburn-by-the-Sea, England, TS12 2HP, United Kingdom","description":"Free Food/Drink, People to chat to, Space to work, Wheelchair Accessible, Toilets, Accessible Toilet, Parking, Child Friendly, Tuesday's session incorporates a Seated Fitness Class from 10:30 - 11:45. No need to join in, you can just sit and listen, have a drink or or sing along. Thursday's session has access to table tennis table, pool table, places to sit, room to work, and prize bingo from 2pm","hours":{"_text":"Tuesday 10.30am-11.45am, Thursday 1pm-3pm","opening":"Tu 10:30-11:45; Th 13:00-15:00"},"title":"Skelton &amp; Brotton Parish Council","url":"https://www.skeltonbrottonpc.co.uk"},"type":"Feature"}
	]
}
