{
	"type": "FeatureCollection",
	"features": [
		{"geometry":{"coordinates":[-0.98398,54.56204],"type":"Point"},"properties":{"_source":"warm_spaces","address":"Skelton Civic Hall, 20 Coniston Road, Saltburn-by-the-Sea, England, TS12 2HP, United Kingdom","description":"Free Food/Drink, People to chat to, Space to work, Wheelchair Accessible, Toilets, Accessible Toilet, Parking, Child Friendly, Tuesday's session incorporates a Seated Fitness Class from 10:30 - 11:45. No need to join in, you can just sit and listen, have a drink or or sing along. Thursday's session has access to table tennis table, pool table, places to sit, room to work, and prize bingo from 2pm","hours":{"_text":"Tuesday 10.30am-11.45am, Thursday 1pm-3pm","opening":"Tu 10:30-11:45; Th 13:00-15:00"},"title":"Skelton &amp; Brotton Parish Council","url":"https://www.skeltonbrottonpc.co.uk"},"type":"Feature"}
	]
}
