{
	"type": "FeatureCollection",
	"features": [
		{"geometry":{"coordinates":[-0.77947,54.24569],"type":"Point"},"properties":{"_source":"warm_welcome","address":"Pickering library, the Ropery, Pickering, North Yorkshire YO18 8DY","hours":{"_text":"Monday: 09:00 - 17:00, Tuesday: 10:00 - 17:00, Thursday: 10:00 - 19:00, Friday: 10:00 - 17:00, Saturday: 10:00 - 14:00","opening":"Mo 09:00-17:00; Tu 10:00-17:00; Th 10:00-19:00; Fr 10:00-17:00; Sa 10:00-14:00"},"title":"Pickering library"},"type":"Feature"}
	]
}
