{
	"type": "FeatureCollection",
	"features": [
		{"geometry":{"coordinates":[-0.77683,54.24477],"type":"Point"},"properties":{"_source":"warm_welcome","address":"The Hungate Centre, North Yorkshire YO18 7DG","description":"A warm welcome awaits at the new Musical Memories Lunch Club for older people — Winter Warmers. There’ll be good company, tea & coffee, crafts & activities, speakers, newspapers, jigsaws, board games, singing and music every Wednesday throughout the winter — in fact a youthful club for the over 60’s! You can pop in just for a warm and a coffee, or you can stay for the whole day... whatever suits you. A hearty soup & roll and a homemade hot pud will be served between 12.00 and 1.00 All for £5 If you would like to join us or want to know more about Winter Warmers the Musical Memories Lunch Club Contact: Ruth on 07527 006402","hours":{"_text":"Wednesday: 10:00 - 15:00","opening":"We 10:00-15:00"},"title":"Hungate Centre"},"type":"Feature"},
		{"geometry":{"coordinates":[-0.77682,54.24477],"type":"Point"},"properties":{"_source":"warm_welcome","address":"Ca V C A, Pickering, North Yorkshire YO18 7DG","description":"Providing a community café, walk and talk sessions, Men in sheds, IT Support, Crafts and 1-1 support.","hours":{"_text":"Thursday: 09:00 - 02:00","opening":"Th 09:00-14:00"},"title":"Hungate Centre"},"type":"Feature"},
		{"geometry":{"coordinates":[-0.93288,54.27054],"type":"Point"},"properties":{"_source":"warm_welcome","address":"Church House, York, North Yorkshire YO62 6AT","description":"Kirkbymoorside Community Library is a warm safe space open to all. It is a friendly, welcoming environment which is totally operated by volunteers. The library is located at the top end of Kirkbymoorside High Street, next to the entrance to the public carpark. We have an up-to-date collection of fiction and nonfiction books and audio books to suit all ages. In addition, we have public access computers which are free for the first hour of use for library members. It is free to join the library.","hours":{"_text":"Monday: 09:30 - 12:30, Tuesday: 09:30 - 12:30, Wednesday: 08:30 - 17:30, Thursday: 09:30 - 12:30, Friday: 09:30 - 17:00, Saturday: 09:30 - 12:30","opening":"Mo 09:30-12:30; Tu 09:30-12:30; We 08:30-17:30; Th 09:30-12:30; Fr 09:30-17:00; Sa 09:30-12:30"},"title":"Kirkbymoorside Community Library"},"type":"Feature"},
		{"geometry":{"coordinates":[-0.77947,54.24569],"type":"Point"},"properties":{"_source":"warm_welcome","address":"Pickering library, The Ropery, Pickering, North Yorkshire YO18 8DY","description":"Pickering's Library loaning books, audiobooks and DVDs. A selection of daily papers is available and computers are available for public use. We have a coffee area with a hot drinks machine.","hours":{"_text":"Monday: 09:00 - 17:00, Tuesday: 10:00 - 17:00, Thursday: 10:00 - 19:00, Friday: 10:00 - 17:00, Saturday: 10:00 - 14:00","opening":"Mo 09:00-17:00; Tu 10:00-17:00; Th 10:00-19:00; Fr 10:00-17:00; Sa 10:00-14:00"},"title":"Pickering Library"},"type":"Feature"}
	]
}
