{
	"type": "FeatureCollection",
	"features": [
		{"geometry":{"coordinates":[-6.23850,55.20322],"type":"Point"},"properties":{"_source":"causeway_coast_and_glens_council","address":"7 Mary Street, Ballycastle, BT54 6QH","description":"Tea and Coffee available","hours":{"_text":"Monday to Thursday 9-5 and Fridays 9-4","opening":"Mo-Th 09:00-05:00; Fr 09:00-04:00"},"title":"Sheskburn Community Centre"},"type":"Feature"},
		{"geometry":{"coordinates":[-6.25598,55.20039],"type":"Point"},"properties":{"_source":"causeway_coast_and_glens_council","address":"5 Leyland Road, Ballycastle, BT54 6DT","contact":"02820762566 or ballycastle.library@librariesni.org.uk","description":"Rhythm & Rhyme (0-4yrs) - Tuesdays 10.30am, Tea & Newspapers - Daily 2.15pm, Knit & Knatter - Thursdays 6.30pm, Job Club and Lego Club - Mondays, Scrabble Club - Thursdays, Chatterbooks (a junior book club) - Saturdays","hours":{"_text":"Mondays 10-1 and 2-5, Tuesdays 10-1 and 2-5, Wednesdays 10-2, Thursdays 1-8, Fridays 10-1 and 2-5, Saturdays 10-1 and 2-5","opening":"Mo 10:00-01:00,02:00-05:00; Tu 10:00-01:00,02:00-05:00; We 10:00-02:00; Th 01:00-08:00; Fr 10:00-01:00,02:00-05:00; Sa 10:00-01:00,02:00-05:00"},"title":"Ballycastle Library"},"type":"Feature"},
		{"geometry":{"coordinates":[-6.24745,55.20258],"type":"Point"},"properties":{"_source":"causeway_coast_and_glens_council","address":"62 Ann Street, Ballycastle, BT54 6AD","contact":"02820248088 or info@solaswellbeing.org.uk","description":"Tea, coffee and a wellbeing library. An activity programme can be found at www.solaswellbeing.org.uk","hours":{"_text":"Mondays 10am-12noon, Tuesdays 9.30am-1pm, Wednesdays 9.30am-1pm and Thursdays 11am-1pm","opening":"Mo 10:00-12:00; Tu 09:30-13:00; We 09:30-13:00; Th 11:00-13:00"},"title":"Solas Wellbeing"},"type":"Feature"},
		{"geometry":{"coordinates":[-6.26294,55.20295],"type":"Point"},"properties":{"_source":"causeway_coast_and_glens_council","address":"Causeway Enterprise Centre, 61 Leyland Road, Ballycastle, BT54 6EZ","contact":"d.smyth@bcwtraining.co.uk","description":"Tea and Coffee, Music, Food from the Community Fridge and Community Support. Coffee and Connect - Tuesdays 2-3pm","hours":{"_text":"Tuesdays 12-3pm and Thursdays 9.30-12noon","opening":"Tu 12:00-15:00; Th 09:30-12:00"},"title":"Community Fridge Ballycastle"},"type":"Feature"}
	]
}
