{
	"type": "FeatureCollection",
	"features": [
		{"geometry":{"coordinates":[-3.43143,56.39206],"type":"Point"},"properties":{"_source":"warm_welcome","address":"St Leonards in the Fields, Marshall Place, Perth, Perthshire PH2 8AG","hours":{"_text":"Monday: 14:00 - 16:00, Sunday: 11:00 - 12:30","opening":"Mo 14:00-16:00; Su 11:00-12:30"},"title":"St Leonard's in the Fields church"},"type":"Feature"}
	]
}
