{
	"type": "FeatureCollection",
	"features": [
		{"geometry":{"coordinates":[-3.02304,53.47753],"type":"Point"},"properties":{"_source":"warm_welcome","address":"Crosby Rd N, Waterloo, Liverpool, Waterloo, Liverpool L22 0LQ","description":"","hours":"Mo 10:00-17:00, Tu 10:00-17:00, We 10:00-17:00, Th 10:00-17:00, Fr 10:00-17:00, Sa 10:00-14:00","title":"Crosby Library "},"type":"Feature"}