{
	"type": "FeatureCollection",
	"features": [
		{"geometry":{"coordinates":[-1.42809,53.23733],"type":"Point"},"properties":{"_source":"warm_welcome","address":"38 Saltergate, Chesterfield, Derbyshire S40 1UH","description":"All are welcome. Children catered for Direct access from the street, all areas wheelchair accessible. TV screen for showing films, play video games , not mainstream TV. Cornerstone Christian Bookshop and Coffee Shop open every day except Wednesday and Sunday 10:00 - 15:00.","hours":"Fr 15:00-18:00","title":"Central Methodist Church, Chesterfield, Derbyshire S40 1UH"},"type":"Feature"},
		{"geometry":{"coordinates":[-1.43497,53.24006],"type":"Point"},"properties":{"_source":"warm_welcome","address":"Chesterfield Baptist Church, Cross Street, Chesterfield S40 4ST","description":" Every Wednesday - Renew Cross Street - Wellbeing Cafe. Saturdays (once a month) - Waste Not Cafe. Please visit our website for further details.","hours":"We 10:00-16:00, Su 18:00-19:30","title":"Chesterfield Baptist Church"},"type":"Feature"},
		{"geometry":{"coordinates":[-1.42478,53.25363],"type":"Point"},"properties":{"_source":"warm_welcome","address":"The Hub, East Stand., Chesterfield, Derbyshire s418nz","description":"","hours":"Mo 17:00-19:30, Tu 17:00-19:30, We 17:00-19:30, Th 17:00-19:30, Fr 17:00-19:30","title":"Chesterfield FC Community Trust"},"type":"Feature"}