{
	"type": "FeatureCollection",
	"features": [
		{"geometry":{"coordinates":[-1.48812,51.21230],"type":"Point"},"properties":{"_source":"warm_welcome","address":"Andover Baptist Church, Charlton Road, Andover, Hampshire SP10 3JH","description":"Open from 17-11-2022.","hours":{"_text":"Thursday: 15:00 - 17:00","opening":"Th 15:00-17:00"},"title":"Andover Baptist Church"},"type":"Feature"},
		{"geometry":{"coordinates":[-1.48016,51.20977],"type":"Point"},"properties":{"_source":"warm_welcome","address":"Andover Library, Chantry Centre, Andover SP10 1LT","hours":{"_text":"Monday: 09:30 - 17:00 / -, Tuesday: 09:30 - 13:30 / -, Wednesday: 09:30 - 17:00 / -, Thursday: 09:30 - 17:00 / -, Friday: 09:30 - 17:00 / -, Saturday: 09:30 - 17:00 / -","opening":"Mo 09:30-17:00; Tu 09:30-13:30; We 09:30-17:00; Th 09:30-17:00; Fr 09:30-17:00; Sa 09:30-17:00"},"title":"Andover Library- Hampshire Libraries"},"type":"Feature"},
		{"geometry":{"coordinates":[-1.47970,51.20631],"type":"Point"},"properties":{"_source":"warm_welcome","address":"31-33 Bridge Street, Andover, Hants SP10 1BE","description":"Open from Thursday 1st December. everyone is welcome We have a pay-it-forward scheme and a sensory playroom","hours":{"_text":"Monday: 09:30 - 14:00, Tuesday: 09:30 - 14:00, Wednesday: 09:30 - 14:00, Thursday: 09:30 - 14:00, Friday: 09:30 - 14:00","opening":"Mo 09:30-14:00; Tu 09:30-14:00; We 09:30-14:00; Th 09:30-14:00; Fr 09:30-14:00"},"title":"the Bridge"},"type":"Feature"},
		{"geometry":{"coordinates":[-1.60199,51.37833],"type":"Point"},"properties":{"_source":"wiltshire_council","description":"A chance to meet, eat and chat just Pop into St. Mary&#39;s Church Great Bedwyn","title":"Thursday Friendship Club - Great Bedwyn -12 - 3pm","url":"https://directory.hertfordshire.gov.uk/Services/2113"},"type":"Feature"}
	]
}
