{
	"type": "FeatureCollection",
	"features": [
		{"geometry":{"coordinates":[-4.56039,53.29316],"type":"Point"},"properties":{"_source":"warm_spaces","address":"Holyhead, Wales, LL65 3BS, United Kingdom","description":"Free Food/Drink, Free Wi-Fi, People to chat to, Toilets, Child Friendly","hours":{"_text":"Fri 12pm-2pm","opening":"Fr 12:00-14:00"},"title":"Tabor Hall"},"type":"Feature"},
		{"geometry":{"coordinates":[-4.27364,53.14109],"type":"Point"},"properties":{"_source":"cyngor_gwynedd","address":"Allt Pafiliwn, Caernarfon, Gwynedd. , LL55 1AS","contact":"Tel: 01286 679463; Email: LlCaernarfon@gwynedd.llyw.cymru","description":"Cyfeiriad: Allt Pafiliwn, Caernarfon, Gwynedd. Côd Post: LL55 1AS Rhif Ffôn: 01286 679463 E-bost: LlCaernarfon@gwynedd.llyw.cymru Dyddiau ac Oriau agor: Llun/Mawrth - Mondayn/Tuesday - 9.30-6.30 Mercher/Iau/Gwener - Wednesday/Thursday/Friday - 9.30-5.00 Sadwrn/Saturday - 9.30-1.00 Beth fydd ar gael yn rhan o’ch “Croeso Cynnes”?: Defnydd o stafell gynnes / The use of a warm room, WIFI, Gweithgareddau / Activities Unrhyw fanylion pellach?:","hours":{"_text":"Llun/Mawrth - Mondayn/Tuesday - 9.30-6.30\nMercher/Iau/Gwener - Wednesday/Thursday/Friday - 9.30-5.00\nSadwrn/Saturday - 9.30-1.00","opening":"We 09:30-05:00; Th 09:30-05:00; Fr 09:30-05:00; Tu 09:30-06:30; Sa 09:30-01:00"},"loc_pcd":true,"title":"Llyfrgell Caernarfon Library"},"type":"Feature"},
		{"geometry":{"coordinates":[-4.27140,53.13835],"type":"Point"},"properties":{"_source":"cyngor_gwynedd","address":"22A Garnon Street, Caernarfon,Gwynedd, LL55 2RB","contact":"Tel: 07919567080; Email: magshug@gmail.com","description":"Cyfeiriad: 22A Garnon Street, Caernarfon,Gwynedd Côd Post: LL55 2RB Rhif Ffôn: 07919567080 E-bost: magshug@gmail.com Dyddiau ac Oriau agor: Prynhawn Dydd iau ar yr 1 af a 3ydd wythnos bob mis o 2-3:30 pm am banad a sgwrs / Thursday afternoon on the 1st and 3rd week of each month from 2pm-3.30pm for a chat and panad Beth fydd ar gael yn rhan o’ch “Croeso Cynnes”?: Defnydd o stafell gynnes / The use of a warm room, Paned / Warm Beverage, Bwyd / Food, Gweithgareddau / Activities, Arall / Other Unrhyw fanylion pellach?: Cyfle i ymuno gyda gwneud cawl a helpu. Opportunity to learn to make soup and to help generally","hours":{"_text":"Prynhawn Dydd iau ar yr 1 af a 3ydd wythnos bob mis o 2-3:30 pm am banad a sgwrs / Thursday afternoon on the 1st and 3rd week of each month from 2pm-3.30pm for a chat and panad"},"loc_pcd":true,"title":"Capel Caersalem"},"type":"Feature"}
	]
}
