{
	"type": "FeatureCollection",
	"features": [
		{"geometry":{"coordinates":[0.41809,51.63612],"type":"Point"},"properties":{"_source":"warm_welcome","address":"140 Perry Street, Billericay , Essex CM12 0NS","description":"","hours":"Su 09:30-12:00","title":"Billericay Baptist Church "},"type":"Feature"}