{
	"type": "FeatureCollection",
	"features": [
		{"geometry":{"coordinates":[-0.04308,52.87800],"type":"Point"},"properties":{"_source":"warm_welcome","address":"Fozdyke playing field, LINCOLNSHIRE PE20 2BX","description":"Village social club open to everyone with no age limits, suitable for families young or old. clubhouse and playing field","hours":{"_text":"Wednesday: 10:00 - 12:00, Saturday: 14:00 - 18:00, Sunday: 14:00 - 18:00","opening":"We 10:00-12:00; Sa 14:00-18:00; Su 14:00-18:00"},"title":"FOZZY'S"},"type":"Feature"},
		{"geometry":{"coordinates":[-0.15365,52.78802],"type":"Point"},"properties":{"_source":"warm_welcome","address":"Spalding Baptist Church, Lincolnshire PE11 1BT","description":"Community Cafe and Social Space where everything is free of charge. We have table tennis, pool and board games available. Also free hot and cold drinks, a cooked lunch, snacks and sweet treats. We also have items of clothing, welfare bags containing toiletries and blankets available free of charge.","hours":{"_text":"Friday: 10:30 - 01:30","opening":"Fr 10:30-01:30"},"title":"Warm Welcome"},"type":"Feature"},
		{"geometry":{"coordinates":[-0.15399,52.78816],"type":"Point"},"properties":{"_source":"warm_spaces","address":"Swan Street, Spalding, England, PE11 1BT, United Kingdom","description":"Free Food/Drink, Advice, People to chat to, Wheelchair Accessible, Toilets, Accessible Toilet, Child Friendly, Basic IT skills, CAP Money Management, Citizens Advice Bureau","hours":{"_text":"Fridays, 9.30am-2.30pm","opening":"Fr 09:30-14:30"},"title":"The Warm Spaces Well of Hope","url":"https://www.spaldingbaptist.org.uk"},"type":"Feature"},
		{"geometry":{"coordinates":[-0.15037,52.78760],"type":"Point"},"properties":{"_source":"warm_spaces","address":"Broad Street, Spalding, England, PE11 1TB, United Kingdom","description":"Free Food/Drink, People to chat to, Wheelchair Accessible, Toilets, Accessible Toilet","hours":{"_text":"Mondays, 10am-4pm","opening":"Mo 10:00-16:00"},"title":"Broad Street Methodist Church","url":"https://www.broadstreetmethodistchurch.co.uk"},"type":"Feature"}
	]
}
