{
	"type": "FeatureCollection",
	"features": [
		{"geometry":{"coordinates":[-0.15399,52.78816],"type":"Point"},"properties":{"_source":"warm_spaces","address":"Swan Street, Spalding, England, PE11 1BT, United Kingdom","description":"Free Food/Drink, Advice, People to chat to, Wheelchair Accessible, Toilets, Accessible Toilet, Child Friendly, Basic IT skills, CAP Money Management, Citizens Advice Bureau","hours":{"_text":"Fridays, 9.30am-2.30pm","opening":"Fr 09:30-14:30"},"title":"The Warm Spaces Well of Hope","url":"https://www.spaldingbaptist.org.uk"},"type":"Feature"},
		{"geometry":{"coordinates":[-0.15037,52.78760],"type":"Point"},"properties":{"_source":"warm_spaces","address":"Broad Street, Spalding, England, PE11 1TB, United Kingdom","description":"Free Food/Drink, People to chat to, Wheelchair Accessible, Toilets, Accessible Toilet","hours":{"_text":"Mondays, 10am-4pm","opening":"Mo 10:00-16:00"},"title":"Broad Street Methodist Church","url":"https://www.broadstreetmethodistchurch.co.uk"},"type":"Feature"}
	]
}
