{
	"type": "FeatureCollection",
	"features": [
		{"geometry":{"coordinates":[-2.38478,52.45233],"type":"Point"},"properties":{"_source":"warm_welcome","address":"Severn centre , Highley , Shropshire Wv16 6JG","description":"All are welcome, children must be supervised We offer a complimentary hot meal, warm packs containing blanket, socks, gloves, stove top & kettle meals, there is also board games - puzzles- cards- dominoes etc. Space to chat and have some company or some peace & keep warm.","hours":"Fr 15:00-18:00","title":"Eat, Meet, Greet "},"type":"Feature"}