{
	"type": "FeatureCollection",
	"features": [
		{"geometry":{"coordinates":[1.75825,52.48263],"type":"Point"},"properties":{"_source":"suffolk_-_rural_coffee_caravan","address":"unit 2, 209 Whapload Road, Lowestoft NR32 1UL, UK","contact":"Phone:07555 41828","hours":{"_text":"Wednesday & Friday 10.00 - 16.00","opening":"We 10:00-16:00; Fr 10:00-16:00"},"title":"WARM SPACES - Re-Utilise"},"type":"Feature"}
	]
}
