{
	"type": "FeatureCollection",
	"features": [
		{"geometry":{"coordinates":[-2.58388,53.59370],"type":"Point"},"properties":{"_source":"warm_welcome","address":"Church Street, Blackrod, Bolton BL6 5EQ","description":"All welcome Please see staff for more information about free activities and sessions","hours":"Mo 10:00-17:00, Th 10:00-19:00, Sa 10:00-13:00","title":"Blackrod Library "},"type":"Feature"}