{
	"type": "FeatureCollection",
	"features": [
		{"geometry":{"coordinates":[-2.12957,57.52116],"type":"Point"},"properties":{"_source":"aberdeenshire_council","address":"Deer Road, Maud, AB42 4EG","contact":"Facebook: https://www.facebook.com/profile.php?id=100080926710575","description":"Cafe is open to the public to drop by for a free cuppa, a cake and a good chat. Occasional guest speakers, outings and activities.","loc_pcd":true,"title":"Conversation Cafe, Maud"},"type":"Feature"},
		{"geometry":{"coordinates":[-2.19833,57.59191],"type":"Point"},"properties":{"_source":"aberdeenshire_council","address":"New Pitsligo and St. John's School (via hub door at the back of the school), School Street, New Pitsligo, AB43 6NE","contact":"Facebook: https://www.facebook.com/profile.php?id=100068833123419","description":"Cafe is open to the public to drop by for a free cuppa, a cake and a good chat. Occasional guest speakers, outings and activities.","loc_pcd":true,"title":"Conversation Cafe, New Pitsligo"},"type":"Feature"},
		{"geometry":{"coordinates":[-2.12957,57.52116],"type":"Point"},"properties":{"_source":"aberdeenshire_council","address":"Deer Road, Maud, Peterhead, AB42 4EG","contact":"Tel: 01771613962","description":"Just Ask project: available for central Buchan residents. One stop Hub for free essential support: food, clothing, energy, financial and welfare issues, baby essentials and equipment, home items, health and wellbeing.","hours":{"_text":"Conversation Cafe: f irst Thursday of every month 10am - 12 noon "},"loc_pcd":true,"title":"Maud Resource Centre","url":"https://www.maudvillagetrust.co.uk/community-service-centre-1"},"type":"Feature"}
	]
}
