{
	"type": "FeatureCollection",
	"features": [
		{"geometry":{"coordinates":[-2.44598,52.70968],"type":"Point"},"properties":{"_source":"warm_welcome","address":"Church Road, Wrockwardine Wood,, Telford TF2 7AH","description":"We are a church in Telford who are open Wednesdays 8.45-11.00 as a drop in warm space where hot drinks are available free of charge We run a FoodBank (tinned and dried foods) and small parcels are available on request from the Church Warden on duty We are fortunate that we have a warm building and are happy to open for people to drop in for hot drinks, a chance to get warm, breakfast (cereal by request or toast). We also have a clothing bank with clothes available from kids to adults. There is always a volunteer available to chat to anyone who might pop in and we have lots of info to hand to help signpost visitors to someone who is best placed to offer any support if required.","hours":{"_text":"Wednesday: 09:00 - 12:00","opening":"We 09:00-12:00"},"title":"Holy Trinity Church Wrockwardine Wood"},"type":"Feature"},
		{"geometry":{"coordinates":[-2.43266,52.71370],"type":"Point"},"properties":{"_source":"warm_welcome","address":"Donnington Community Hub, St Matthews Road, Telford, Shropshire tf3 7pr","description":"a warm space to socialise and get hot drinks and snacks","hours":{"_text":"Monday: 09:30 - 12:30, Tuesday: 09:30 - 12:30, Wednesday: 09:30 - 12:30, Thursday: 09:30 - 12:30, Friday: 09:30 - 12:30","opening":"Mo 09:30-12:30; Tu 09:30-12:30; We 09:30-12:30; Th 09:30-12:30; Fr 09:30-12:30"},"title":"Meet & Eat"},"type":"Feature"},
		{"geometry":{"coordinates":[-2.14775,52.90214],"type":"Point"},"properties":{"_source":"warm_welcome","address":"Stone Library, Staffordshire ST15 8AT","description":"Stone library has two floors. There is a sofa area downstairs and a table upstairs and down. There is a public toilet with a baby change facility. A reading nook for children. Tables and chairs for little ones to colour in. Coffee and tea will be served Monday-Friday 10.00am-12.00pm & 2.00pm-4.00pm (apart from Wednesdays when we close at 1pm) Contact: 01785 895585 or visit our Instagram page @staffordstonelibraries","hours":{"_text":"Monday: 09:00 - 05:00, Tuesday: 09:00 - 06:00, Wednesday: 09:00 - 01:00, Thursday: 09:00 - 05:00, Friday: 09:00 - 06:00, Saturday: 09:00 - 04:00","opening":"Mo 09:00-17:00; Tu 09:00-18:00; We 09:00-13:00; Th 09:00-17:00; Fr 09:00-18:00; Sa 09:00-16:00"},"title":"Stone Library"},"type":"Feature"}
	]
}
