{
	"type": "FeatureCollection",
	"features": [
		{"geometry":{"coordinates":[-2.11823,52.80556],"type":"Point"},"properties":{"_source":"warm_spaces","address":"Church Lane, Stafford, England, ST16 2AW, United Kingdom","description":"Free Food/Drink, Free Wi-Fi, Advice, People to chat to, Space to work, Wheelchair Accessible, Toilets, Accessible Toilet, Child Friendly","hours":{"_text":"Monday 2pm-4pm, Tuesday 12pm-2pm","opening":"Mo 14:00-16:00; Tu 12:00-14:00"},"title":"Church Lane Church","url":"https://www.church-lane.org.uk"},"type":"Feature"},
		{"geometry":{"coordinates":[-2.11550,52.80365],"type":"Point"},"properties":{"_source":"warm_spaces","address":"Bailey Street, Stafford, England, ST17 4BG, United Kingdom","description":"Free Food/Drink, People to chat to, Wheelchair Accessible, Toilets, Accessible Toilet, Child Friendly, games and activities","hours":{"_text":"Wednesday 3pm-5pm, Thursday 1pm-3pm","opening":"We 15:00-17:00; Th 13:00-15:00"},"title":"Stafford Baptist Church","url":"https://www.staffordbaptistchurch.co.uk"},"type":"Feature"},
		{"geometry":{"coordinates":[-2.13275,52.79444],"type":"Point"},"properties":{"_source":"warm_spaces","address":"Auden Way, Stafford, England, ST17 9TX, United Kingdom","description":"Free Food/Drink, Free Wi-Fi, Device Charging, People to chat to, Wheelchair Accessible, Toilets, Accessible Toilet, Parking, Child Friendly","hours":{"_text":"Tuesdays 10am-1pm","opening":"Tu 10:00-13:00"},"title":"Elevate Highfields","url":"https://risingbrook.org/elevate"},"type":"Feature"},
		{"geometry":{"coordinates":[-2.37996,52.75844],"type":"Point"},"properties":{"_source":"warm_spaces","address":"5 Wallshead Way, Church Aston, Newport, England, TF10 9JG, United Kingdom","description":"Free Food/Drink, Free Wi-Fi, Device Charging, People to chat to, Wheelchair Accessible, Toilets, Accessible Toilet, Parking","hours":{"_text":"Wednesdays 10:30am-3pm","opening":"We 10:30-15:00"},"title":"St Andrew's, Church Aston ‘Community Cuppa’","url":"https://www.churchastonstandrews.com"},"type":"Feature"}
	]
}
