{
	"type": "FeatureCollection",
	"features": [
		{"geometry":{"coordinates":[-2.11457,51.45703],"type":"Point"},"properties":{"_source":"warm_spaces","address":"Timber Street, Chippenham, England, SN15 3EJ, United Kingdom","description":"Free Wi-Fi, Device Charging, Advice, Space to work, Wheelchair Accessible, Child Friendly, Computer Access, Games, jigsaws, books, magazines.","hours":{"_text":"Monday 10am-7pm; Tuesday 9am-5pm; Wednesday 9am-1pm; Thursday 9am-7pm; Friday 9am-7pm; Saturday 9am-5pm","opening":"Mo 10:00-19:00; Tu 09:00-17:00; We 09:00-13:00; Th 09:00-19:00; Fr 09:00-19:00; Sa 09:00-17:00"},"title":"Chippenham Library","url":"https://www.wiltshire.gov.uk/libraries"},"type":"Feature"},
		{"geometry":{"coordinates":[-2.19271,51.43176],"type":"Point"},"properties":{"_source":"warm_spaces","address":"Beechfield Road, Corsham, England, SN13 9DN, United Kingdom","description":"Free Wi-Fi, Device Charging, Advice, Space to work, Food/Drink for sale, Wheelchair Accessible, Toilets, Accessible Toilet, Parking, Child Friendly, Computer Access, books, colouring and jigsaws","hours":{"_text":"Monday, Friday 9am-7pm, Tues/Wed/Thurs/Sat 9am-5pm","opening":"Mo 09:00-19:00; Fr 09:00-19:00; Tu 09:00-17:00; We 09:00-17:00; Th 09:00-17:00; Sa 09:00-17:00"},"title":"Corsham Library","url":"https://wiltshire.gov.uk"},"type":"Feature"}
	]
}
