{
	"type": "FeatureCollection",
	"features": [
		{"geometry":{"coordinates":[-3.83259,53.32429],"type":"Point"},"properties":{"_source":"warm_welcome","address":"Gloddaeth Church, Chapel Street, Llandudno LL30 2SY","description":"Open from 09/11/2022. A warm welcome for everyone","hours":"We 14:00-18:00","title":"Gloddaeth Church, Llandudno"},"type":"Feature"},
		{"geometry":{"coordinates":[-3.77332,53.31887],"type":"Point"},"properties":{"_source":"warm_welcome","address":"St David's Church, Penrhyn Bay, Llandudno LL30 3PA","description":"Open from 02-11-2022.","hours":"We 09:30-12:00","title":"St David's Church"},"type":"Feature"},
		{"geometry":{"coordinates":[-3.83363,53.32235],"type":"Point"},"properties":{"_source":"warm_spaces","address":"Lloyd Street, Llandudno, Wales, LL30","title":"Tea &amp; Toast","url":"https://www.emmanuelchurchllandudno.org.uk"},"type":"Feature"}
	]
}
