{
	"type": "FeatureCollection",
	"features": [
		{"geometry":{"coordinates":[-4.34735,53.40950],"type":"Point"},"properties":{"_source":"warm_spaces","address":"17 Mona Street, Amlwch, Wales, LL68 9AN","title":"Ffiws Amlwch","url":"https://www.facebook.com/ffiwsamlwch"},"type":"Feature"}
	]
}
