{
	"type": "FeatureCollection",
	"features": [
		{"geometry":{"coordinates":[-68.65690,45.24261],"type":"Point"},"properties":{"_source":"warm_welcome","address":"70 Main Street, Kirkliston, Edinburgh EH29 9AB","description":"We are a church on Main Street in Kirkliston. We would love to invite you to come in to our space if you need us.","hours":{"_text":"Thursday: 09:30 - 11:15, Friday: 10:00 - 12:00, Sunday: 10:30 - 12:30","opening":"Th 09:30-11:15; Fr 10:00-12:00; Su 10:30-12:30"},"title":"Kirkliston Community Church"},"type":"Feature"}
	]
}
