{
	"type": "FeatureCollection",
	"features": [
		{"geometry":{"coordinates":[-1.16142,51.09114],"type":"Point"},"properties":{"_source":"warm_welcome","address":"Alresford Library, 20 Broad Street, New Alresford SO24 9AQ","description":"There is timed parking at the front of the building on Broad Street but this is HCC-run","hours":"Tu 13:00-17:00, Th 09:30-13:30, Fr 13:00-17:00, Sa 09:30-13:30","title":"Alresford Library- Hampshire Libraries"},"type":"Feature"}