{
	"type": "FeatureCollection",
	"features": [
		{"geometry":{"coordinates":[-4.74499,56.19634],"type":"Point"},"properties":{"_source":"argyll_and_bute_third_sector_interface","address":"Shore Road, Arrochar, G83 7AB","description":"Warm welcome, cup of tea, conversation, with speakers and activities.","hours":{"_text":"The Open Doors group offer a warm welcome on Mondays between 10am – 12.30pm ."},"loc_pcd":true,"title":"3 Villages Community Hall"},"type":"Feature"},
		{"geometry":{"coordinates":[-4.74812,56.19415],"type":"Point"},"properties":{"_source":"argyll_and_bute_third_sector_interface","address":"11 Kirkfield Place,Arrochar G83 7AE","description":"The Craft and Chat Group continues to run every Wednesday afternoon from 1pm until 2.30pm. It runs all year round, with the exception of the first two weeks in January when they generally take a break. However, if there is a need to keep the Church open for these two Wednesday&apos;s, it could be arranged.","hours":{"_text":" Wednesdays 1 – 2.30pm ","opening":"We 13:00-14:30"},"loc_pcd":true,"title":"Arrochar Parish Church"},"type":"Feature"},
		{"geometry":{"coordinates":[-4.90058,56.17086],"type":"Point"},"properties":{"_source":"argyll_and_bute_third_sector_interface","address":"Hall Road, Lochgoilhead, PA24 8AQ","description":"A warm space, hot meal and free internet access, open to all the Lochgoil community.","hours":{"_text":" Monday 6-8pm ","opening":"Mo 18:00-20:00"},"loc_pcd":true,"title":"Lochgoilhead Village Hall"},"type":"Feature"}
	]
}
