{
	"type": "FeatureCollection",
	"features": [
		{"geometry":{"coordinates":[-4.67409,55.61517],"type":"Point"},"properties":{"_source":"warm_welcome","address":"church street, Irvine, North Ayrshire KA12 8DD","description":"Our focus is for families and young adults but ALL are welcome. We run a community cafe on Tuesday and Thursdays 10-2 for cheap meals or if cannot afford it we will privde soup and sandwich for free and a warm space please ask at reception. Church services are on Sunday 10.30-12 with hot drinks after.","hours":{},"title":"Fullarton ConneXions"},"type":"Feature"},
		{"geometry":{"coordinates":[-4.67409,55.61517],"type":"Point"},"properties":{"_source":"warm_welcome","address":"church street, Irvine, North Ayrshire KA12 8DD","description":"Our focus is for families and young adults but ALL are welcome. We run a community cafe on Tuesday and Thursdays 10-2 for cheap meals or if cannot afford it we will privde soup and sandwich for free and a warm space please ask at reception. Church services are on Sunday 10.30-12 with hot drinks after.","hours":{},"title":"Fullarton ConneXions"},"type":"Feature"},
		{"geometry":{"coordinates":[-4.81101,55.64380],"type":"Point"},"properties":{"_source":"warm_welcome","address":"150a Glasgow Street, Ardrossan, North Ayrshire KA22 8EU","description":"Open from 31/10/2022.","hours":{"_text":"Monday: 10:00 - 20:00, Tuesday: 10:00 - 20:00, Wednesday: 10:00 - 20:00, Thursday: 10:00 - 20:00","opening":"Mo 10:00-20:00; Tu 10:00-20:00; We 10:00-20:00; Th 10:00-20:00"},"title":"North Ayrshire Foodbank"},"type":"Feature"},
		{"geometry":{"coordinates":[-4.81101,55.64380],"type":"Point"},"properties":{"_source":"warm_welcome","address":"150a Glasgow Street, Ardrossan, North Ayrshire KA22 8EU","description":"Open from 31/10/2022.","hours":{"_text":"Monday: 10:00 - 20:00, Tuesday: 10:00 - 20:00, Wednesday: 10:00 - 20:00, Thursday: 10:00 - 20:00","opening":"Mo 10:00-20:00; Tu 10:00-20:00; We 10:00-20:00; Th 10:00-20:00"},"title":"North Ayrshire Foodbank"},"type":"Feature"}
	]
}
