{
	"type": "FeatureCollection",
	"features": [
		{"geometry":{"coordinates":[-4.68572,55.75347],"type":"Point"},"properties":{"_source":"warm_welcome","address":"The Salvation Army, Ayrshire KA25 6HN","description":"A listening ear with support of a job club, assistance with CVs, volunteering chats, digital skills and more. Refreshments served.","hours":{"_text":"Wednesday: 13:00 - 15:00","opening":"We 13:00-15:00"},"title":"A Wee Welcome In"},"type":"Feature"},
		{"geometry":{"coordinates":[-4.68149,55.75641],"type":"Point"},"properties":{"_source":"warm_welcome","address":"The Montgomery Community Hub, Kilbirnie, Ayrshire KA25 7JE","description":"Come and say hi to the Discovery Group and have a chat or join in our activities on Tuesdays 2 to 4 pm contact","hours":{"_text":"Tuesday: 14:00 - 16:00","opening":"Tu 14:00-16:00"},"title":"Montgomery Court Hub"},"type":"Feature"},
		{"geometry":{"coordinates":[-4.66353,55.61633],"type":"Point"},"properties":{"_source":"warm_welcome","address":"49 Bank Street, Irvine, Ayrshire KA12 0LP","description":"SPACE OPENING ON 25th November 2025** Our space is designed to feel like a cosy retreat—a place where warmth and friendliness are at the heart of everything we do. It’s a snug, welcoming environment where people can relax, connect, and feel truly at home, we aim to create a supportive atmosphere that fosters comfort, community, and care.","hours":{"_text":"Wednesday: 10:00 - 02:00","opening":"We 10:00-14:00"},"title":"NODA comfy cuppa"},"type":"Feature"},
		{"geometry":{"coordinates":[-4.85668,55.68959],"type":"Point"},"properties":{"_source":"warm_welcome","address":"Main Street, West Kilbride, North Ayrshire KA23 9LJ","description":"Free Wi-Fi, soup and sandwich and other refreshments available! Newspapers, board games and toys for toddlers. Why not bring your own craft? Please note that the Church is also open on a Tuesday morning from 10.30am for our weekly Coffee morning - all welcome. Sunday Service is at 10.30am with hot drinks afterwards. Please go to our website to see when the building is also open at other times: wkpc.church","hours":{"_text":"Friday: 12:00 - 15:00","opening":"Fr 12:00-15:00"},"title":"Warm Hub"},"type":"Feature"}
	]
}
