{
	"type": "FeatureCollection",
	"features": [
		{"geometry":{"coordinates":[-4.68475,55.35482],"type":"Point"},"properties":{"_source":"warm_spaces","address":"Culzean Road, Maybole, Scotland, KA19 7DE","hours":{"_text":"10am "},"title":"Carrick Centre","url":"https://www.carrickcentre.co.uk"},"type":"Feature"}
	]
}
