{
	"type": "FeatureCollection",
	"features": [
		{"geometry":{"coordinates":[-4.70969,55.21229],"type":"Point"},"properties":{"_source":"warm_welcome","address":"2 Glenginnet road, Barr, South Ayrshire KA26 9TU","description":"Barr Community Shop and Cafe is a community-owned Welcome Space in the village of Barr in South Ayrshire. Anyone is welcome during opening hours for a cup of tea and a chat in our community cafe. We support the community by providing a shop, cafe and Post Office. It is run by paid staff and volunteers.","hours":{"_text":"Monday: 09:00 - 14:00 / 18:00 - 19:00, Tuesday: 09:00 - 14:00 / 18:00 - 19:00, Wednesday: 09:00 - 14:00 / 18:00 - 19:00, Thursday: 09:00 - 14:00 / 18:00 - 19:00, Friday: 09:00 - 14:00 / 18:00 - 19:00, Saturday: 10:00 - 15:00 / 18:00 - 19:00, Sunday: 10:00 - 15:00","opening":"Mo 09:00-14:00,18:00-19:00; Tu 09:00-14:00,18:00-19:00; We 09:00-14:00,18:00-19:00; Th 09:00-14:00,18:00-19:00; Fr 09:00-14:00,18:00-19:00; Sa 10:00-15:00,18:00-19:00; Su 10:00-15:00"},"title":"Barr Community Shop and Cafe"},"type":"Feature"},
		{"geometry":{"coordinates":[-4.68398,55.35501],"type":"Point"},"properties":{"_source":"warm_welcome","address":"the carrick centre, South Ayrshire, South Ayrshire KA19 7DE","description":"The Carrick Centre, a beautiful purpose-built community facility, great café with free soft play, bike/E-Bike hire, a church and lots of activities daily. Located next to train and bus routes. Something for everyone - come and see us.","hours":{"_text":"Monday: 09:00 - 16:30, Tuesday: 09:00 - 19:00, Wednesday: 09:00 - 16:30, Thursday: 09:00 - 16:30, Friday: 09:00 - 16:30, Saturday: 09:00 - 14:30","opening":"Mo 09:00-16:30; Tu 09:00-19:00; We 09:00-16:30; Th 09:00-16:30; Fr 09:00-16:30; Sa 09:00-14:30"},"title":"The Carrick Centre"},"type":"Feature"}
	]
}
