{
	"type": "FeatureCollection",
	"features": [
		{"geometry":{"coordinates":[-4.74220,51.80808],"type":"Point"},"properties":{"_source":"warm_spaces","address":"Unit 1 B, Redstone Road, Narberth, Wales, SA67 7ES, United Kingdom","description":"Free Food/Drink, Free Wi-Fi, Device Charging","hours":{"_text":"9am-5pm"},"title":"Quayside Care","url":"https://www.quaysidecareltd.co.uk"},"type":"Feature"}
	]
}
