{
	"type": "FeatureCollection",
	"features": [
		{"geometry":{"coordinates":[-4.91834,51.67519],"type":"Point"},"properties":{"_source":"warm_welcome","address":"The Tanyard, Pembrokeshire SA71 4EA","description":"Youth Centre open in the daytime for public sessions as well.","hours":{"_text":"Monday: 16:00 - 19:00, Tuesday: 16:00 - 18:00 / 18:30 - 20:30, Wednesday: 16:00 - 18:00 / 18:30 - 20:30, Thursday: 16:00 - 19:00, Friday: 17:00 - 19:00 / 19:30 - 21:30","opening":"Mo 16:00-19:00; Tu 16:00-18:00,18:30-20:30; We 16:00-18:00,18:30-20:30; Th 16:00-19:00; Fr 17:00-19:00,19:30-21:30"},"title":"Tanyard Youth Project"},"type":"Feature"},
		{"geometry":{"coordinates":[-4.74220,51.80808],"type":"Point"},"properties":{"_source":"warm_spaces","address":"Unit 1 B, Redstone Road, Narberth, Wales, SA67 7ES, United Kingdom","description":"Free Food/Drink, Free Wi-Fi, Device Charging","hours":{"_text":"9am-5pm"},"title":"Quayside Care","url":"https://www.quaysidecareltd.co.uk"},"type":"Feature"}
	]
}
