{
	"type": "FeatureCollection",
	"features": [
		{"geometry":{"coordinates":[-4.72213,51.73148],"type":"Point"},"properties":{"_source":"warm_welcome","address":"St Mary’s Church, Begelly, Pembrokeshire SA68","hours":{"_text":"Monday: 13:00 - 15:00","opening":"Mo 13:00-15:00"},"title":"Anglican churches of Saundersfoot, Begelly, Amroth, and Ludchurch"},"type":"Feature"},
		{"geometry":{"coordinates":[-4.82677,51.69806],"type":"Point"},"properties":{"_source":"warm_welcome","address":"Carew Wesley Methodist Hall, Carew, , Tenby SA70 8SL","description":"Open from 05-12-2022.","hours":{"_text":"Monday: 13:00 - 16:00","opening":"Mo 13:00-16:00"},"title":"Carew Wesley Methodist Church"},"type":"Feature"},
		{"geometry":{"coordinates":[-4.74220,51.80808],"type":"Point"},"properties":{"_source":"warm_spaces","address":"Unit 1 B, Redstone Road, Narberth, Wales, SA67 7ES","hours":{"_text":"9am-5pm"},"title":"Quayside Care","url":"https://www.quaysidecareltd.co.uk"},"type":"Feature"}
	]
}
