{
	"type": "FeatureCollection",
	"features": [
		{"geometry":{"coordinates":[-4.79037,51.64784],"type":"Point"},"properties":{"_source":"warm_welcome","address":"Giraldus Centre, Tenby, Dyfed SA70 7TN","description":"A community centre run by volunteers with a large hall, two kitchens, three meeting rooms and ample parking. The centre is all on one level and fully accessible, with disabled toilets.","hours":{"_text":"Tuesday: 10:00 - 12:00, Wednesday: 16:00 - 19:00, Thursday: 11:00 - 12:00, Friday: 10:00 - 15:00","opening":"Tu 10:00-12:00; We 16:00-19:00; Th 11:00-12:00; Fr 10:00-15:00"},"title":"Giraldus Centre"},"type":"Feature"},
		{"geometry":{"coordinates":[-4.91834,51.67519],"type":"Point"},"properties":{"_source":"warm_welcome","address":"The Tanyard, Pembrokeshire SA71 4EA","description":"Youth Centre open in the daytime for public sessions as well.","hours":{"_text":"Monday: 16:00 - 19:00, Tuesday: 16:00 - 18:00 / 18:30 - 20:30, Wednesday: 16:00 - 18:00 / 18:30 - 20:30, Thursday: 16:00 - 19:00, Friday: 17:00 - 19:00 / 19:30 - 21:30","opening":"Mo 16:00-19:00; Tu 16:00-18:00,18:30-20:30; We 16:00-18:00,18:30-20:30; Th 16:00-19:00; Fr 17:00-19:00,19:30-21:30"},"title":"Tanyard Youth Project"},"type":"Feature"},
		{"geometry":{"coordinates":[-4.71011,51.67680],"type":"Point"},"properties":{"_source":"warm_welcome","address":"Augustus Place Community Hall, Pembrokeshire, Pembrokeshire SA70 8dj","hours":{"_text":"Monday: 10:30 - 12:30","opening":"Mo 10:30-12:30"},"title":"The Tenby Project Coffee Morning"},"type":"Feature"},
		{"geometry":{"coordinates":[-4.74220,51.80808],"type":"Point"},"properties":{"_source":"warm_spaces","address":"Unit 1 B, Redstone Road, Narberth, Wales, SA67 7ES, United Kingdom","description":"Free Food/Drink, Free Wi-Fi, Device Charging","hours":{"_text":"9am-5pm"},"title":"Quayside Care","url":"https://www.quaysidecareltd.co.uk"},"type":"Feature"}
	]
}
