{
	"type": "FeatureCollection",
	"features": [
		{"geometry":{"coordinates":[-0.53676,54.43438],"type":"Point"},"properties":{"_source":"warm_welcome","address":"Wesley Road, Robin Hoods Bay, North Yorkshire YO22 4RW","description":"","hours":"Th 10:30-14:00","title":"Robin Hood's Bay Methodist Church"},"type":"Feature"},
		{"geometry":{"coordinates":[-0.53615,54.43417],"type":"Point"},"properties":{"_source":"warm_welcome","address":"Thorpe Lane, Robin Hood’s Bay, Whitby, N Yorkshire YO22 4TU","description":"","hours":"We 10:30-12:30","title":"St Stephen’s Church"},"type":"Feature"},
		{"geometry":{"coordinates":[-0.61444,54.48325],"type":"Point"},"properties":{"_source":"warm_welcome","address":"Windsor Terrace, Whitby, North Yorkshire YO21 1EY","description":"","hours":"Mo 09:30-17:00, Tu 09:30-19:00, Th 09:30-17:00, Fr 09:30-17:00, Sa 10:00-13:00","title":"Whitby Library"},"type":"Feature"},
		{"geometry":{"coordinates":[-0.62371,54.48743],"type":"Point"},"properties":{"_source":"warm_welcome","address":"Windsor Terrace, Whitby, North Yorkshire yo213ea","description":"","hours":"Mo 09:00-17:00, Tu 09:30-19:00, Th 09:30-19:00, Fr 09:30-17:00, Sa 10:00-13:00","title":"Whitby Library"},"type":"Feature"}
	]
}
