{
	"type": "FeatureCollection",
	"features": [
		{"geometry":{"coordinates":[1.43948,51.35840],"type":"Point"},"properties":{"_source":"warm_spaces","address":"2 Queens Road, Broadstairs, England, CT10 1NU, United Kingdom","description":"Free Food/Drink, Free Wi-Fi, Wheelchair Accessible, Toilets, Accessible Toilet, We are just starting and will assess the need. We will adapt activates to the needs of those who attend.","hours":{"_text":"Wednesday 1pm-4pm","opening":"We 13:00-16:00"},"title":"Queens Road Baptist Church","url":"https://www.broadstairsbaptist.org.uk/welcome.htm"},"type":"Feature"},
		{"geometry":{"coordinates":[1.41457,51.38062],"type":"Point"},"properties":{"_source":"warm_spaces","address":"Holy Trinity Church, Saint Mary&#39;s Avenue, Margate, England, CT9 3TN, United Kingdom","description":"Advice, People to chat to","hours":{"_text":"6pm-11pm"},"title":"Thanet Safe Haven"},"type":"Feature"},
		{"geometry":{"coordinates":[1.42805,51.36882],"type":"Point"},"properties":{"_source":"warm_spaces","address":"St Peter&#39;s Recreation Ground, Callis Court Road/Grange Road, Broadstairs, England, CT10, United Kingdom","description":"Device Charging, People to chat to, Pay it forward scheme, Food/Drink for sale, we sometimes have free bread and pastries. Toddler group on Wednesday mornings","hours":{"_text":"Tuesday Thursday and Friday, 9am-2pm","opening":"Tu 09:00-14:00; Th 09:00-14:00; Fr 09:00-14:00"},"title":"The Pavilion Youth &amp; Community Cafe","url":"http://thepavilioncommunitycafe.co.uk"},"type":"Feature"}
	]
}
