{
	"type": "FeatureCollection",
	"features": [
		{"geometry":{"coordinates":[-6.76844,54.50407],"type":"Point"},"properties":{"_source":"warm_spaces","address":"Vineyard Church Dungannon, The Storehouse, 4 Church Lane, Dungannon, Northern Ireland, BT71 6AA, United Kingdom","description":"Free Food/Drink, Free Wi-Fi, Device Charging, People to chat to, Space to work, Quiet Prayer room","hours":{"_text":"Abide Tues, 10sm-2pm"},"title":"Vineyard Church Dungannon","url":"http://www.vineyarddungannon.co.uk"},"type":"Feature"}
	]
}
