{
	"type": "FeatureCollection",
	"features": [
		{"geometry":{"coordinates":[-6.77970,54.50259],"type":"Point"},"properties":{"_source":"warm_welcome","address":"The Junction, 12 Beechvalley Way, Dungannon BT70 1BS","description":"All welcome - The ground floor foyer of The Junction offers comfortable seating and free tea or coffee. Call in to read a paper or meet a friend.","hours":{"_text":"Monday: 10:00 - 16:00, Tuesday: 10:00 - 16:00, Wednesday: 10:00 - 16:00, Thursday: 10:00 - 16:00, Friday: 10:00 - 16:00","opening":"Mo 10:00-16:00; Tu 10:00-16:00; We 10:00-16:00; Th 10:00-16:00; Fr 10:00-16:00"},"title":"STEP - The Junction"},"type":"Feature"},
		{"geometry":{"coordinates":[-6.77970,54.50259],"type":"Point"},"properties":{"_source":"warm_welcome","address":"The Junction, 12 Beechvalley Way, Dungannon BT70 1BS","description":"All welcome - The ground floor foyer of The Junction offers comfortable seating and free tea or coffee. Call in to read a paper or meet a friend.","hours":{"_text":"Monday: 10:00 - 16:00, Tuesday: 10:00 - 16:00, Wednesday: 10:00 - 16:00, Thursday: 10:00 - 16:00, Friday: 10:00 - 16:00","opening":"Mo 10:00-16:00; Tu 10:00-16:00; We 10:00-16:00; Th 10:00-16:00; Fr 10:00-16:00"},"title":"STEP - The Junction"},"type":"Feature"},
		{"geometry":{"coordinates":[-6.76844,54.50407],"type":"Point"},"properties":{"_source":"warm_spaces","address":"Vineyard Church Dungannon, The Storehouse, 4 Church Lane, Dungannon, Northern Ireland, BT71 6AA","hours":{"_text":"Abide Tues, 10sm-2pm"},"title":"Vineyard Church Dungannon","url":"http://www.vineyarddungannon.co.uk"},"type":"Feature"}
	]
}
