{
	"type": "FeatureCollection",
	"features": [
		{"geometry":{"coordinates":[-3.79907,56.15380],"type":"Point"},"properties":{"_source":"warm_welcome","address":"The Green, Brook St., Alva, Clackmannanshire FK12 5JQ","description":"","hours":"We 10:00-12:00","title":"Alva Baptist Church"},"type":"Feature"}