{
	"type": "FeatureCollection",
	"features": [
		{"geometry":{"coordinates":[-2.96830,56.46117],"type":"Point"},"properties":{"_source":"warm_spaces","address":"High Street, Dundee, Scotland, DD1 1TD","hours":{"_text":""},"title":"St Paul's Cathedral, Dundee","url":"https://www.saintpaulscathedral.net"},"type":"Feature"},
		{"geometry":{"coordinates":[-3.06281,56.46094],"type":"Point"},"properties":{"_source":"perth_and_kinross_council","address":"ALL SOULS CHURCH 59 MAIN ST INVERGOWRIE DD2 5BA","description":"Warm space, refreshments, chat. Every Thursday 10am-12pm","hours":{"_text":"Warm space, refreshments, chat. Every Thursday 10am-12pm","opening":"Th 10:00-12:00"},"title":"All Souls Church"},"type":"Feature"}
	]
}
