{
	"type": "FeatureCollection",
	"features": [
		{"geometry":{"coordinates":[-0.02416,52.97855],"type":"Point"},"properties":{"_source":"warm_welcome","address":"County Hall, Boston, Lincolnshire PE21 6DY","description":"It is free to join and use the library and everyone is welcome. Alongside free access to books, computers, casual and study seating, the Library runs a host of free activities for adults and children including Connect Over A Cuppa community coffee morning every Thursday 10am-12noon, there is no charge for refreshments.","hours":{"_text":"Monday: 09:00 - 17:00, Tuesday: 09:00 - 17:00, Wednesday: 09:00 - 17:00, Thursday: 09:00 - 18:00, Friday: 09:00 - 17:00, Saturday: 09:00 - 16:00","opening":"Mo 09:00-17:00; Tu 09:00-17:00; We 09:00-17:00; Th 09:00-18:00; Fr 09:00-17:00; Sa 09:00-16:00"},"title":"Boston Library"},"type":"Feature"},
		{"geometry":{"coordinates":[-0.02868,52.97468],"type":"Point"},"properties":{"_source":"warm_welcome","address":"restore church, Boston, Lincolnshire PE21 8UJ","description":"Open from 14.11.2022. A free warm space, activities available","hours":{"_text":"Monday: 10:00 - 14:00, Tuesday: 10:00 - 14:00","opening":"Mo 10:00-14:00; Tu 10:00-14:00"},"title":"Restore Church"},"type":"Feature"},
		{"geometry":{"coordinates":[-0.04340,52.95245],"type":"Point"},"properties":{"_source":"warm_spaces","address":"289 London Road, Boston, England, PE21 7DD","hours":{"_text":"11am-11pm"},"title":"The Pincushion Inn","url":"https://www.facebook.com/profile.php?id=100086526795177"},"type":"Feature"}
	]
}
