{
	"type": "FeatureCollection",
	"features": [
		{"geometry":{"coordinates":[-2.84223,55.54857],"type":"Point"},"properties":{"_source":"warm_welcome","address":"Selkirk Public Library, Selkirkshire TD7 4LE","description":"Public Library","hours":{"_text":"Tuesday: 14:00 - 17:00, Thursday: 10:00 - 13:00","opening":"Tu 14:00-17:00; Th 10:00-13:00"},"title":"Selkirk Public Library"},"type":"Feature"}
	]
}
