{
	"type": "FeatureCollection",
	"features": [
		{"geometry":{"coordinates":[-3.03586,52.86450],"type":"Point"},"properties":{"_source":"warm_welcome","address":"The Whole Life Christian Centre, Oswestry, Shropshire SY11 2LQ","description":"SPACE OPENING ON 3rd November 2025** A warm and welcome space to come and have a cup of tea or coffee and relax with your neighbours.","hours":{"_text":"Monday: 09:00 - 17:00, Tuesday: 09:00 - 17:00, Wednesday: 09:00 - 17:00, Friday: 09:00 - 18:00, Saturday: 09:00 - 15:00","opening":"Mo 09:00-17:00; Tu 09:00-17:00; We 09:00-17:00; Fr 09:00-18:00; Sa 09:00-15:00"},"title":"Cafe Life Winter Warmer"},"type":"Feature"},
		{"geometry":{"coordinates":[-3.05763,52.85665],"type":"Point"},"properties":{"_source":"warm_welcome","address":"Church Street, Oswestry, Shropshire SY11 2SY","description":"Community chat cafe.","hours":{"_text":"Tuesday: 10:30 - 12:30","opening":"Tu 10:30-12:30"},"title":"Place of Welcome at St Oswald's, Oswestry"},"type":"Feature"}
	]
}
