{
	"type": "FeatureCollection",
	"features": [
		{"geometry":{"coordinates":[-3.03586,52.86450],"type":"Point"},"properties":{"_source":"warm_welcome","address":"The Whole Life Christian Centre, Oswestry, Shropshire SY11 2LQ","description":"SPACE OPENING ON 3rd November 2025** A warm and welcome space to come and have a cup of tea or coffee and relax with your neighbours.","hours":{"_text":"Monday: 09:00 - 17:00, Tuesday: 09:00 - 17:00, Wednesday: 09:00 - 17:00, Friday: 09:00 - 18:00, Saturday: 09:00 - 15:00","opening":"Mo 09:00-17:00; Tu 09:00-17:00; We 09:00-17:00; Fr 09:00-18:00; Sa 09:00-15:00"},"title":"Cafe Life Winter Warmer"},"type":"Feature"},
		{"geometry":{"coordinates":[-3.04091,52.89808],"type":"Point"},"properties":{"_source":"warm_welcome","address":"All Saint's Church Hall,, Gobowen, Oswestry SY11 3LL","description":"Thursdays we are open for refreshments, company, conversation etc in our Community Cafe 14:30-16:00. Sundays we are open for our church service at 11am. Hot drinks are available after the service in the hall from 12:15.","hours":{"_text":"Thursday: 14:30 - 16:00, Sunday: 11:00 - 13:00","opening":"Th 14:30-16:00; Su 11:00-13:00"},"title":"Community Cafe at All Saints' Church Gobowen"},"type":"Feature"},
		{"geometry":{"coordinates":[-2.83453,52.89911],"type":"Point"},"properties":{"_source":"warm_welcome","address":"52 Clarendon Place, St Georges Cross, Glasgow","description":"A Weekly Lunch Club from 12-2:30pm in our New Community Hub next to the Church. A lovely warm welcoming space where you will get food, a heat and a nice place to relax with others.","hours":{"_text":"Wednesday: 12:00 - 14:30, Sunday: 10:30 - 11:30","opening":"We 12:00-14:30; Su 10:30-11:30"},"title":"Findlay Church Community Hub"},"type":"Feature"},
		{"geometry":{"coordinates":[-3.05751,52.85680],"type":"Point"},"properties":{"_source":"warm_welcome","address":"Church Street, Oswestry, Shropshire SY11 2SY","description":"Community chat cafe.","hours":{"_text":"Tuesday: 10:30 - 12:30","opening":"Tu 10:30-12:30"},"title":"Place of Welcome at St Oswald's, Oswestry"},"type":"Feature"}
	]
}
