{
	"type": "FeatureCollection",
	"features": [
		{"geometry":{"coordinates":[-3.05288,52.86230],"type":"Point"},"properties":{"_source":"warm_welcome","address":"Chapel, Albert Road, Oswestry , Shropshire SY11 1NF","description":"Open to anyone during these hours, but optional groups: Tues - WOW creative writers, Thurs AM - toddlers, PM - knitting/croche, Fri AM - seniors","hours":{"_text":"Tuesday: 13:00 - 15:00 / - Fortnightly, Thursday: 09:30 - 15:30, Friday: 09:30 - 12:00, Sunday: 10:00 - 12:30","opening":"Tu 13:00-15:00; Th 09:30-15:30; Fr 09:30-12:00; Su 10:00-12:30"},"title":"Albert Road Evangelical Church"},"type":"Feature"},
		{"geometry":{"coordinates":[-3.04036,52.89782],"type":"Point"},"properties":{"_source":"warm_welcome","address":"All Saint's Church Hall, Chirk Road, Gobowen, Oswestry SY11 3LL","description":"Thursdays we are open for refreshments, company, conversation etc in our Community Cafe 14:30-16:00. Sundays we are open for our church service at 11am. Hot drinks are available after the service in the hall from 12:15.","hours":{"_text":"Thursday: 14:30 - 16:00, Sunday: 11:00 - 13:00","opening":"Th 14:30-16:00; Su 11:00-13:00"},"title":"Community Cafe at All Saints' Church Gobowen"},"type":"Feature"},
		{"geometry":{"coordinates":[-3.04036,52.89782],"type":"Point"},"properties":{"_source":"warm_welcome","address":"All Saint's Church Hall, Chirk Road, Gobowen, Oswestry SY11 3LL","description":"Thursdays we are open for refreshments, company, conversation etc in our Community Cafe 14:30-16:00. Sundays we are open for our church service at 11am. Hot drinks are available after the service in the hall from 12:15.","hours":{"_text":"Thursday: 14:30 - 16:00, Sunday: 11:00 - 13:00","opening":"Th 14:30-16:00; Su 11:00-13:00"},"title":"Community Cafe at All Saints' Church Gobowen"},"type":"Feature"},
		{"geometry":{"coordinates":[-3.05751,52.85680],"type":"Point"},"properties":{"_source":"warm_welcome","address":"Church Street, Oswestry, Shropshire SY112SY","hours":{"_text":"Tuesday: 10:30 - 12:30","opening":"Tu 10:30-12:30"},"title":"Place of Welcome at St Oswald's, Oswestry"},"type":"Feature"}
	]
}
