{
	"type": "FeatureCollection",
	"features": [
		{"geometry":{"coordinates":[-2.96439,50.87156],"type":"Point"},"properties":{"_source":"warm_welcome","address":"Holyrood Lace Mill, Holyrood Street, Chard, Somerset TA20 2YA","description":"Public library","hours":{"_text":"Monday: 09:30 - 16:30, Tuesday: 09:30 - 16:30, Thursday: 09:30 - 17:00, Friday: 09:30 - 16:30, Saturday: 09:30 - 12:30","opening":"Mo 09:30-16:30; Tu 09:30-16:30; Th 09:30-17:00; Fr 09:30-16:30; Sa 09:30-12:30"},"title":"Chard Library"},"type":"Feature"},
		{"geometry":{"coordinates":[-2.96244,50.87303],"type":"Point"},"properties":{"_source":"warm_welcome","address":"Forefront Community Centre, 42 Fore Street,, Chard, Somerset TA20 1QA","description":"Mondays starts with a craft morning Wednesdays starts with a coffee morning Both include a simple lunch - soup and roll","hours":{"_text":"Monday: 10:00 - 14:00, Wednesday: 10:00 - 14:00","opening":"Mo 10:00-14:00; We 10:00-14:00"},"title":"Forefront Community Church/Centre"},"type":"Feature"},
		{"geometry":{"coordinates":[-2.90896,50.92622],"type":"Point"},"properties":{"_source":"warm_welcome","address":"Ilminster Bowling & Tennis Club, Ilminster, Somerset TA19 0BN","description":"The club has a large clubhouse which is open 7days a week and is a warm environment to be part of . We have many great members who use the club for multiple reason , social , bowls , tennis , snooker , cards , bridge , canasta and more .","hours":{"_text":"Monday: 10:00 - 22:00, Tuesday: 10:00 - 22:00, Wednesday: 10:00 - 22:00, Thursday: 10:00 - 22:00, Friday: 10:00 - 22:00, Saturday: 10:00 - 22:00, Sunday: 10:00 - 22:00","opening":"Mo 10:00-22:00; Tu 10:00-22:00; We 10:00-22:00; Th 10:00-22:00; Fr 10:00-22:00; Sa 10:00-22:00; Su 10:00-22:00"},"title":"Ilminster Bowling & Tennis Club"},"type":"Feature"},
		{"geometry":{"coordinates":[-2.91085,50.92470],"type":"Point"},"properties":{"_source":"warm_welcome","address":"Ditton Street, Ilminster, Somerset TA19 0BW","description":"Public library","hours":{"_text":"Monday: 09:30 - 12:00, Tuesday: 09:30 - 16:30, Wednesday: 09:30 - 12:00, Friday: 09:30 - 16:30, Saturday: 09:30 - 12:00","opening":"Mo 09:30-12:00; Tu 09:30-16:30; We 09:30-12:00; Fr 09:30-16:30; Sa 09:30-12:00"},"title":"Ilminster Library"},"type":"Feature"}
	]
}
