{
	"type": "FeatureCollection",
	"features": [
		{"geometry":{"coordinates":[-2.17958,52.62824],"type":"Point"},"properties":{"_source":"warm_welcome","address":"The Olde Vicarage, 7 Bilbrook Road, Wolverhampton, Staffordshire WV8 1EU","description":"","hours":"We 12:00-18:00","title":"Bilbrook Initiatives Hub"},"type":"Feature"}