{
	"type": "FeatureCollection",
	"features": [
		{"geometry":{"coordinates":[-1.78422,53.65811],"type":"Point"},"properties":{"_source":"warm_welcome","address":"Lee Street, Hillhouse, Huddersfield, West Yorkshire HD1 6HF","description":" All our libraries are heated, comfortable to stay in for long periods of time - they have a range of both comfy seating, and more functional furniture for study or computer use. A place to keep warm, meet friends, sit and read and take part in activities.","hours":"Tu 10:00-13:00, We 13:00-17:00, Fr 14:00-18:00, Sa 11:00-15:00","title":"Birkby Fartown Library"},"type":"Feature"},
		{"geometry":{"coordinates":[-1.83783,53.68489],"type":"Point"},"properties":{"_source":"warm_welcome","address":"Elland Library, Coronation Street, Elland HX5 0DF","description":" Please note Elland Library will close at 1pm on Saturday 24th December and reopen on Tuesday 3rd January 2023","hours":"Mo 10:00-17:00, Tu 10:00-17:00, We 10:00-13:00, Th 10:00-18:00, Fr 10:00-17:00, Sa 10:00-16:00","title":"Calderdale MBC"},"type":"Feature"},
		{"geometry":{"coordinates":[-1.79361,53.68939],"type":"Point"},"properties":{"_source":"warm_welcome","address":"Rastrick Library, Crowtrees Lane Rastrick , Brighouse HD6 3NE","description":" We will be closed for Christmas from 1pm Christmas Eve until 10am Tuesday 3rd January. We are closed for lunch 1 - 2pm every day.","hours":"Mo 10:00-17:00, Tu 10:00-17:00, We 10:00-13:00, Th 10:00-17:00, Fr 10:00-17:00, Sa 10:00-13:00","title":"Calderdale MBC"},"type":"Feature"},
		{"geometry":{"coordinates":[-1.76876,53.66840],"type":"Point"},"properties":{"_source":"warm_welcome","address":"2a Chestnut Street, Sheepbridge, Huddersfield, West Yorkshire HD2 1HJ","description":" All our libraries are heated, comfortable to stay in for long periods of time - they have a range of both comfy seating, and more functional furniture for study or computer use. A place to keep warm, meet friends, sit and read and take part in activities.","hours":"Mo 09:00-17:00, Tu 09:00-17:00, We 09:00-17:00, Th 09:00-17:00, Fr 09:00-17:00","title":"Chestnut Centre"},"type":"Feature"}