{
	"type": "FeatureCollection",
	"features": [
		{"geometry":{"coordinates":[-2.78469,55.42726],"type":"Point"},"properties":{"_source":"warm_welcome","address":"North Bridge Street, Hawick, Scottish Borders TD9 9QT","description":"Public Library open to all. People are welcome to bring their own hot drinks and flasks in","hours":{"_text":"Monday: 09:30 - 17:00, Tuesday: 09:30 - 18:00, Thursday: 09:30 - 17:00, Friday: 09:30 - 16:00","opening":"Mo 09:30-17:00; Tu 09:30-18:00; Th 09:30-17:00; Fr 09:30-16:00"},"title":"Hawick Library"},"type":"Feature"},
		{"geometry":{"coordinates":[-2.55225,55.47811],"type":"Point"},"properties":{"_source":"warm_welcome","address":"Millfield Gardens, Jedburgh, Scottish Borders TD8 6ER","description":"Staying socially connected and maintaining an active lifestyle are key elements of staying healthy. But not everyone finds it so easy to get out and about and stay social, especially those who live alone or are less mobile. That’s where our social activities services come in. We run a wide range of clubs, groups and events in local communities, many of them staffed by our volunteers. They’re great places to meet old friends, make new ones, refresh existing skills or try something new. Our social activities are available online and in person depending on where you live.","hours":{"_text":"Monday: 10:00 - 14:00, Wednesday: 10:00 - 14:00","opening":"Mo 10:00-14:00; We 10:00-14:00"},"title":"Jedburgh"},"type":"Feature"},
		{"geometry":{"coordinates":[-2.64540,55.57100],"type":"Point"},"properties":{"_source":"warm_welcome","address":"St. Boswells Village Hall, Melrose, Roxburghshire TD6 0AL","description":"Staying socially connected and maintaining an active lifestyle are key elements of staying healthy. But not everyone finds it so easy to get out and about and stay social, especially those who live alone or are less mobile. That’s where our social activities services come in. We run a wide range of clubs, groups and events in local communities, many of them staffed by our volunteers. They’re great places to meet old friends, make new ones, refresh existing skills or try something new. Our social activities are available online and in person depending on where you live.","hours":{"_text":"Tuesday: 10:00 - 14:00","opening":"Tu 10:00-14:00"},"title":"St Boswells"},"type":"Feature"}
	]
}
