{
	"type": "FeatureCollection",
	"features": [
		{"geometry":{"coordinates":[-2.75131,54.55661],"type":"Point"},"properties":{"_source":"cumbria_council","contact":"Tel: 01931 719202","description":"Welcoming community pub environment with board games and snug with real fire. Events are frequently hosted such as quizzes, macrame, darts and guitar playing.","hours":{},"title":"Bampton Valley Community Pub","url":"https://new.cumbria.gov.uk/node/3912"},"type":"Feature"}
	]
}
